pwrpy/TransactionBuilder.py
pwrpy/TransactionDecoder.py
pwrpy/Utils/AES256.py
pwrpy/Utils/Deterministic.py
pwrpy/Utils/Falcon.py
pwrpy/Utils/Hex.py
pwrpy/Utils/__init__.py
pwrpy/Utils/falcon_wrapper.py
pwrpy/Utils/libfalcon.so
pwrpy/__init__.py
pwrpy/models/Block.py
pwrpy/models/Delegator.py
pwrpy/models/MerkleTree.py
pwrpy/models/Response.py
pwrpy/models/Transaction.py
pwrpy/models/VIDA.py
pwrpy/models/Validator.py
pwrpy/models/__init__.py
pwrpy/models/power_kv.py
pwrpy/models/power_kv_cached.py
pwrpy/pwrsdk.py
pwrpy/pwrwallet.py
pwrpy/signer.py
pwrpy-6.2.1.dist-info/LICENSE
pwrpy-6.2.1.dist-info/METADATA
pwrpy-6.2.1.dist-info/WHEEL
pwrpy-6.2.1.dist-info/RECORD
