Metadata-Version: 2.1
Name: pwrpy
Version: 6.2.1
Summary: PWRPY is a Python library for interacting with the PWR network.
Home-page: https://github.com/pwrlabs/pwrpy
License: MIT
Keywords: pwr,network,python,library
Author: PWR Labs
Author-email: devservices@pwrlabs.io
Requires-Python: >=3.8
Classifier: License :: OSI Approved :: MIT License
Classifier: Programming Language :: Python :: 3
Classifier: Programming Language :: Python :: 3.8
Classifier: Programming Language :: Python :: 3.9
Classifier: Programming Language :: Python :: 3.10
Classifier: Programming Language :: Python :: 3.11
Classifier: Programming Language :: Python :: 3.12
Requires-Dist: coincurve (>=20.0.0,<21.0.0)
Requires-Dist: cryptography (>=44.0.2,<45.0.0)
Requires-Dist: ecdsa (>=0.19.0,<0.20.0)
Requires-Dist: eth-account (>=0.13.3,<0.14.0)
Requires-Dist: liboqs-pwr (>=0.12.1,<0.13.0)
Requires-Dist: mnemonic (>=0.21,<0.22)
Requires-Dist: python-dotenv (>=1.0.0,<2.0.0)
Requires-Dist: requests (>=2.32.3,<3.0.0)
Requires-Dist: safe-pysha3 (>=1.0.4,<2.0.0)
Project-URL: Documentation, https://docs.pwrlabs.io/
Project-URL: Repository, https://github.com/pwrlabs/pwrpy
